setup.cfg
setup.py
smapp_toolkit/__init__.py
smapp_toolkit/plotting.py
smapp_toolkit.egg-info/PKG-INFO
smapp_toolkit.egg-info/SOURCES.txt
smapp_toolkit.egg-info/dependency_links.txt
smapp_toolkit.egg-info/requires.txt
smapp_toolkit.egg-info/top_level.txt
smapp_toolkit/twitter/__init__.py
smapp_toolkit/twitter/aggregator.py
smapp_toolkit/twitter/base_tweet_collection.py
smapp_toolkit/twitter/bson_tweet_collection.py
smapp_toolkit/twitter/counter_functions.py
smapp_toolkit/twitter/figure_helpers.py
smapp_toolkit/twitter/figure_makers.py
smapp_toolkit/twitter/mongo_tweet_collection.py