Metadata-Version: 1.0
Name: smapp-toolkit
Version: 0.1.39
Summary: NYU SMaPP lab toolkit
Home-page: http://smapp.nyu.edu
Author: NYU SMaPP
Author-email: smapp_programmer-group@nyu.edu
License: GPLv2
Platform: UNKNOWN
